[
  {
    "question": "How to C1?",
    "options": ["Option1", "Option2", "Option3", "Option4"],
    "answer": "Option1"
  },
  {
    "question": "How to C2?",
    "options": ["Option1", "Option2", "Option3", "Option4"],
    "answer": "Option2"
  },
  {
    "question": "How to C3?",
    "options": ["Option1", "Option2", "Option3", "Option4"],
    "answer": "Option3"
  },
  {
    "question": "How to C4?",
    "options": ["Option1", "Option2", "Option3", "Option4"],
    "answer": "Option4"
  },
  {
    "question": "How to C5?",
    "options": ["Option1", "Option2", "Option3", "Option4"],
    "answer": "Option4"
  },
  {
    "question": "How to C6?",
    "options": ["Option1", "Option2", "Option3", "Option4"],
    "answer": "Option4"
  },
  {
    "question": "How to C7?",
    "options": ["Option1", "Option2", "Option3", "Option4"],
    "answer": "Option4"
  },
  {
    "question": "How to C8?",
    "options": ["Option1", "Option2", "Option3", "Option4"],
    "answer": "Option4"
  },
  {
    "question": "How to C9?",
    "options": ["Option1", "Option2", "Option3", "Option4"],
    "answer": "Option4"
  },
  {
    "question": "How to C10?",
    "options": ["Option1", "Option2", "Option3", "Option4"],
    "answer": "Option4"
  },
  {
    "question": "How to C11?",
    "options": ["Option1", "Option2", "Option3", "Option4"],
    "answer": "Option4"
  },
  {
    "question": "How to C12?",
    "options": ["Option1", "Option2", "Option3", "Option4"],
    "answer": "Option4"
  },
  {
    "question": "How to C13?",
    "options": ["Option1", "Option2", "Option3", "Option4"],
    "answer": "Option4"
  },
  {
    "question": "How to C14?",
    "options": ["Option1", "Option2", "Option3", "Option4"],
    "answer": "Option4"
  },
  {
    "question": "How to C15?",
    "options": ["Option1", "Option2", "Option3", "Option4"],
    "answer": "Option4"
  }
]